verifycas/__init__.py
verifycas/verifycas.py
verifycas-0.1.dist-info/METADATA
verifycas-0.1.dist-info/WHEEL
verifycas-0.1.dist-info/top_level.txt
verifycas-0.1.dist-info/RECORD
