Metadata-Version: 2.1
Name: verifycas
Version: 0.1
Summary: 验证casno号是否符合世界标准
Home-page: http://www.zhaomeng.net
Author: zhaomeng
Author-email: 1737605956@qq.com
License: UNKNOWN
Platform: UNKNOWN
